cubesdk/__init__.py
cubesdk/cache.py
cubesdk/client.py
cubesdk/constant.py
cubesdk/exceptions.py
cubesdk/helper.py
cubesdk-0.1.3.dist-info/licenses/LICENSE
cubesdk-0.1.3.dist-info/METADATA
cubesdk-0.1.3.dist-info/WHEEL
cubesdk-0.1.3.dist-info/top_level.txt
cubesdk-0.1.3.dist-info/RECORD
