Metadata-Version: 2.4
Name: cubesdk
Version: 0.1.3
Summary: CubeSDK: Secure secret management client
Author-email: Anthony Nwaizuzu <tonychuks7@gmail.com>
License: MIT
Keywords: sdk,secret-management,cube
Classifier: Programming Language :: Python :: 3
Classifier: License :: OSI Approved :: MIT License
Classifier: Operating System :: OS Independent
Requires-Python: >=3.9
License-File: LICENSE
Requires-Dist: requests>=2.31.0
Requires-Dist: python-dotenv>=1.0.0
Dynamic: license-file
